game_extraction_toolbox-0.2.0.dist-info/licenses/LICENSE
gex/__init__.py
gex/toolbox.py
gex/commands/version.py
gex/commands/archive/__init__.py
gex/commands/archive/archive.py
gex/commands/archive/arc/__init__.py
gex/commands/archive/arc/arc.py
gex/commands/archive/arc/extract.py
gex/commands/archive/kpka/__init__.py
gex/commands/archive/kpka/extract.py
gex/commands/archive/kpka/kpka.py
gex/commands/archive/zip/__init__.py
gex/commands/archive/zip/list.py
gex/commands/archive/zip/zip.py
gex/commands/file/__init__.py
gex/commands/file/deinterleave.py
gex/commands/file/diff.py
gex/commands/file/file.py
gex/commands/file/hash.py
gex/commands/file/identify.py
gex/commands/file/slice.py
gex/commands/finder/__init__.py
gex/commands/finder/bulk.py
gex/commands/finder/finder.py
gex/commands/postprocess/__init__.py
gex/commands/postprocess/postprocess.py
gex/commands/postprocess/wii/__init__.py
gex/commands/postprocess/wii/cleanrip.py
gex/commands/postprocess/wii/wii.py
gex/commands/tasks/__init__.py
gex/commands/tasks/details.py
gex/commands/tasks/extract.py
gex/commands/tasks/list.py
gex/commands/tasks/tasks.py
gex/lib/archive/__init__.py
gex/lib/archive/arc.py
gex/lib/archive/bplist-mbundle.py
gex/lib/archive/kpka.py
gex/lib/archive/kvq.py
gex/lib/archive/lzma.py
gex/lib/archive/prs.py
gex/lib/archive/zip.py
gex/lib/contrib/bputil.py
gex/lib/file/__init__.py
gex/lib/file/identify.py
gex/lib/tasks/basetask.py
gex/lib/tasks/copytask.py
gex/lib/tasks/helpers.py
gex/lib/tasks/splicetask.py
gex/lib/tasks/task_template.py
gex/lib/tasks/zipsplicetask.py
gex/lib/tasks/impl/__init__.py
gex/lib/tasks/impl/acac/__init__.py
gex/lib/tasks/impl/acac/metadata.json
gex/lib/tasks/impl/ags_digdug/__init__.py
gex/lib/tasks/impl/ags_digdug/metadata.json
gex/lib/tasks/impl/ags_galaga/__init__.py
gex/lib/tasks/impl/ags_galaga/metadata.json
gex/lib/tasks/impl/ags_mspacman/__init__.py
gex/lib/tasks/impl/ags_mspacman/metadata.json
gex/lib/tasks/impl/ags_pacman/__init__.py
gex/lib/tasks/impl/ags_pacman/metadata.json
game_extraction_toolbox-0.2.0.dist-info/METADATA
game_extraction_toolbox-0.2.0.dist-info/WHEEL
game_extraction_toolbox-0.2.0.dist-info/entry_points.txt
game_extraction_toolbox-0.2.0.dist-info/top_level.txt
game_extraction_toolbox-0.2.0.dist-info/RECORD
