Metadata-Version: 2.4
Name: game-extraction-toolbox
Version: 0.2.0
Summary: CLI Tools for investigating game files and extracting known packages
Author-email: Shawn McNaughton <shawngmc@gmail.com>
License: MIT License
Project-URL: Homepage, https://github.com/shawngmc/game-extraction-toolbox
Project-URL: Bug Tracker, https://github.com/shawngmc/game-extraction-toolbox/issues
Requires-Python: >=3.9
License-File: LICENSE
Requires-Dist: bitarray>=2.6.0
Requires-Dist: click>=8.1.3
Requires-Dist: click-log>=0.4.0
Requires-Dist: psutil>=5.9.1
Requires-Dist: rich>=12.5.1
Requires-Dist: texttable>=1.6.4
Dynamic: license-file
